happy_shop/__init__.py
happy_shop/apps.py
happy_shop/filters.py
happy_shop/forms.py
happy_shop/signals.py
happy_shop/tests.py
happy_shop/urls.py
happy_shop/utils.py
happy_shop/admin/__init__.py
happy_shop/admin/admin.py
happy_shop/admin/forms.py
happy_shop/admin/happy_admin.py
happy_shop/admin/widget.py
happy_shop/api/__init__.py
happy_shop/api/api_urls.py
happy_shop/api/backend.py
happy_shop/api/filters.py
happy_shop/api/pagination.py
happy_shop/api/permissions.py
happy_shop/api/serializers/__init__.py
happy_shop/api/serializers/base.py
happy_shop/api/serializers/comment.py
happy_shop/api/serializers/goods.py
happy_shop/api/serializers/order.py
happy_shop/api/views/__init__.py
happy_shop/api/views/base.py
happy_shop/api/views/comment.py
happy_shop/api/views/goods.py
happy_shop/api/views/order.py
happy_shop/conf/__init__.py
happy_shop/conf/default_settings.py
happy_shop/migrations/0001_initial.py
happy_shop/migrations/0002_alter_happyshoporderinfo_freight_and_more.py
happy_shop/migrations/0003_alter_happyshopordersku_price.py
happy_shop/migrations/0004_happyshoprate.py
happy_shop/migrations/0005_happyshoprate_owner.py
happy_shop/migrations/0006_remove_happyshoprate_tag_happyshoprate_comment.py
happy_shop/migrations/0007_happyshoprate_add_date_happyshoprate_is_del_and_more.py
happy_shop/migrations/__init__.py
happy_shop/models/__init__.py
happy_shop/models/comment.py
happy_shop/models/goods.py
happy_shop/models/models.py
happy_shop/models/order.py
happy_shop/pay/__init__.py
happy_shop/pay/alipay/__init__.py
happy_shop/pay/alipay/alipay.py
happy_shop/pay/alipay/keys/app_private_key.pem
happy_shop/pay/alipay/keys/app_public_key.pem
happy_shop/pay/wechatpay/wechatpay.py
happy_shop/static/happy_shop/css/buefy.min.css
happy_shop/static/happy_shop/css/bulma-dashboard.css
happy_shop/static/happy_shop/css/bulma-dashboard.css.map
happy_shop/static/happy_shop/css/bulma-dashboard.min.css
happy_shop/static/happy_shop/css/bulma-dashboard.min.css.map
django_happy_shop-1.1.3.dist-info/LICENSE
django_happy_shop-1.1.3.dist-info/METADATA
django_happy_shop-1.1.3.dist-info/WHEEL
django_happy_shop-1.1.3.dist-info/top_level.txt
django_happy_shop-1.1.3.dist-info/RECORD
