Metadata-Version: 2.1
Name: django-happy-shop
Version: 1.1.3
Summary: 一个可快速集成到任何django项目的轻量级商城模块！
Home-page: http://www.lotdoc.cn/blog/topic/detail/5/
Author: 幸福关中
Author-email: 1158920674@qq.com
License: MIT
Project-URL: Bug Tracker, http://www.lotdoc.cn
Classifier: Programming Language :: Python :: 3
Classifier: License :: OSI Approved :: MIT License
Classifier: Operating System :: OS Independent
Requires-Python: >=3.6
License-File: LICENSE
Requires-Dist: Django (>=3.2)
Requires-Dist: Pillow (>=9.0.1)
Requires-Dist: python-alipay-sdk (>=3.0.4)
Requires-Dist: django-cors-headers (>=3.11.0)
Requires-Dist: django-crispy-forms (>=1.14.0)
Requires-Dist: django-filter (>=21.1)
Requires-Dist: coreapi (>=2.3.3)
Requires-Dist: djangorestframework (>=3.13.1)
Requires-Dist: drf-extensions (>=0.7.1)
